fitbit_api/__init__.py
fitbit_api/exceptions.py
fitbit_api-2.0.0.dist-info/METADATA
fitbit_api-2.0.0.dist-info/RECORD
fitbit_api-2.0.0.dist-info/WHEEL
fitbit_api-2.0.0.dist-info/top_level.txt
