Metadata-Version: 2.1
Name: fitbit-api
Version: 2.0.0
Summary: Fitbit API Client
Home-page: https://github.com/lizlecrone/fitbit-api
Author: Liz LeCrone
Author-email: lizlecrone@gmail.com
License: UNKNOWN
Platform: UNKNOWN
Classifier: Programming Language :: Python :: 3
Classifier: License :: OSI Approved :: MIT License
Classifier: Operating System :: OS Independent
Requires-Python: >=3.6
Requires-Dist: requests
Requires-Dist: requests-oauthlib
